xiaomi_flashable_firmware_creator_gui/__init__.py
xiaomi_flashable_firmware_creator_gui/__main__.py
xiaomi_flashable_firmware_creator_gui/icon.png
xiaomi_flashable_firmware_creator_gui/main.py
xiaomi_flashable_firmware_creator_gui/components/__init__.py
xiaomi_flashable_firmware_creator_gui/components/about.py
xiaomi_flashable_firmware_creator_gui/components/drop_space.py
xiaomi_flashable_firmware_creator_gui/components/input_dialog.py
xiaomi_flashable_firmware_creator_gui/components/message_box.py
xiaomi_flashable_firmware_creator_gui/data/settings.json
xiaomi_flashable_firmware_creator_gui/helpers/__init__.py
xiaomi_flashable_firmware_creator_gui/helpers/layout.py
xiaomi_flashable_firmware_creator_gui/helpers/misc.py
xiaomi_flashable_firmware_creator_gui/helpers/settings.py
xiaomi_flashable_firmware_creator_gui/i18n/af.qm
xiaomi_flashable_firmware_creator_gui/i18n/ar.qm
xiaomi_flashable_firmware_creator_gui/i18n/bn-IN.qm
xiaomi_flashable_firmware_creator_gui/i18n/bn.qm
xiaomi_flashable_firmware_creator_gui/i18n/ca.qm
xiaomi_flashable_firmware_creator_gui/i18n/cs.qm
xiaomi_flashable_firmware_creator_gui/i18n/da.qm
xiaomi_flashable_firmware_creator_gui/i18n/de-DE.qm
xiaomi_flashable_firmware_creator_gui/i18n/de.qm
xiaomi_flashable_firmware_creator_gui/i18n/el.qm
xiaomi_flashable_firmware_creator_gui/i18n/en.qm
xiaomi_flashable_firmware_creator_gui/i18n/en_US.qm
xiaomi_flashable_firmware_creator_gui/i18n/es-ES.qm
xiaomi_flashable_firmware_creator_gui/i18n/fa.qm
xiaomi_flashable_firmware_creator_gui/i18n/fi.qm
xiaomi_flashable_firmware_creator_gui/i18n/fr.qm
xiaomi_flashable_firmware_creator_gui/i18n/ga-IE.qm
xiaomi_flashable_firmware_creator_gui/i18n/he.qm
xiaomi_flashable_firmware_creator_gui/i18n/hi.qm
xiaomi_flashable_firmware_creator_gui/i18n/hr.qm
xiaomi_flashable_firmware_creator_gui/i18n/hu.qm
xiaomi_flashable_firmware_creator_gui/i18n/hy-AM.qm
xiaomi_flashable_firmware_creator_gui/i18n/id.qm
xiaomi_flashable_firmware_creator_gui/i18n/it.qm
xiaomi_flashable_firmware_creator_gui-2.3.18.dist-info/METADATA
xiaomi_flashable_firmware_creator_gui-2.3.18.dist-info/WHEEL
xiaomi_flashable_firmware_creator_gui-2.3.18.dist-info/entry_points.txt
xiaomi_flashable_firmware_creator_gui-2.3.18.dist-info/licenses/LICENSE
xiaomi_flashable_firmware_creator_gui-2.3.18.dist-info/RECORD
