Metadata-Version: 2.3
Name: xiaomi_flashable_firmware_creator_gui
Version: 2.3.18
Summary: Create flashable firmware zip from MIUI Recovery and HyperOS ROMs!
Author-email: yshalsager <contact@yshalsager.com>
License:                     GNU GENERAL PUBLIC LICENSE
License-File: LICENSE
Keywords: android,firmware,xiaomi
Requires-Python: >=3.12
Requires-Dist: pyqt5>=5.15.11
Requires-Dist: xiaomi-flashable-firmware-creator>=2.2.14
